casfs/__init__.py
casfs/_version.py
casfs/base.py
casfs/util.py
tests/casfs/__init__.py
tests/casfs/test_base.py
casfs-0.1.2.dist-info/LICENSE
casfs-0.1.2.dist-info/LICENSE_SHORT
casfs-0.1.2.dist-info/METADATA
casfs-0.1.2.dist-info/WHEEL
casfs-0.1.2.dist-info/top_level.txt
casfs-0.1.2.dist-info/RECORD
