Metadata-Version: 2.1
Name: casfs
Version: 0.1.2
Summary: Content-Addressable filesystem over Pyfilesystem2.
Home-page: https://github.com/google/casfs
Author: Sam Ritchie
Author-email: samritchie@google.com
License: UNKNOWN
Platform: UNKNOWN
Requires-Python: >=3.5.3
Requires-Dist: fs
Requires-Dist: fs-gcsfs
